{
  "command": {
    "start": {
      "signedUp": "🎉 Ти успішно зареєструвався",
      "updated": "📝 Твої дані були оновлені, тепер ти можеш отримувати сповіщення"
    },
    "cards": {
      "add": {
        "chooseBank": "👇 Який банк?",
        "sendCardNumber": "💳 Відправ номер картки",
        "invalidCardNumber": "❌ Номер картки введений невірно, спробуй ще раз: /addcard",
        "invalidCardNumberLength": "❌ Номер картки повинен складатися з 16 цифр, спробуй ще раз: /addcard",
        "saved": "✅ Картку було збережено: *{number}* \\({bank}\\)"
      },
      "delete": {
        "nothingToDelete": "🤷 У тебе ще немає карток\\. Додати картку можна за допомогою /addcard",
        "chooseCard": "👇 Обери картку для видалення:",
        "card": "{number} ({bank})",
        "deleted": "🗑 Картку було видалено"
      },
      "get": {
        "chooseUser": "👇 Обери користувача:",
        "user": "{name} (@{username})",
        "nothingToGet": {
          "user": "🤷 У користувача *{name}* ще немає карток",
          "myself": "🤷 У тебе ще немає карток\\. Додати картку можна за допомогою /addcard"
        },
        "chooseCard": {
          "user": "👇 Обери картку користувача *{name}*:",
          "myself": "👇 Обери свою картку:"
        },
        "card": "{number} ({bank})"
      }
    },
    "debts": {
      "ingoingDebts": [
        "⬅️ Тобі винні:",
        "{debts}"
      ],
      "noIngoingDebts": "✅ Тобі ніхто нічого не винен",
      "outgoingDebts": [
        "➡️ Ти винен:",
        "{debts}"
      ],
      "noOutgoingDebts": "✅ Ти нікому нічого не винен",
      "debt": "\\- *{name}*: {amount}",
      "noDescription": "без опису",
      "withPhoto": "з фото",
      "withoutPhoto": "без фото",
      "incompleteUser": "💡 Щоб отримувати повідомлення про платежі та чеки, виконай /start в особистому чаті з ботом"
    },
    "payments": {
      "help": [
        "💸 Переглянути **платежі** можна тут:",
        "{viewUrl}",
        "",
        "➕ Додати платіж:",
        "{createUrl}"
      ]
    },
    "receipts": {
      "help": [
        "🧾 Переглянути **чеки** можна тут:",
        "{viewUrl}",
        "",
        "➕ Додати чек:",
        "{createUrl}"
      ]
    },
    "rollCalls": {
      "group": [
        "🗣 Переглянути **переклички** можна тут:",
        "{viewUrl}",
        "",
        "➕ Створити нову перекличку:",
        "{createUrl}"
      ],
      "private": [
        "🗣 Переглянути **переклички** можна тут:",
        "{viewUrl}"
      ]
    },
    "title": {
      "help": [
        "✍️ Відредагувати **підписи** можна тут:",
        "{editUrl}"
      ]
    }
  },
  "groupChatOnly": "❌ Цю команду можна виконати лише у груповому чаті",
  "privateChatOnly": "❌ Цю команду можна виконати лише в особистому чаті з ботом",
  "rollCalls": {
    "noOneToMention": "❌ Немає кого пінганути чи у бота недостатньо даних про цей чат",
    "defaultPollTitle": "Обери відповідь",
    "message": {
      "withText": [
      "*{text}*",
        "",
        "{mentions}"
      ],
      "withoutText": "{mentions}"
    },
    "mention": {
      "withUsername": "@{username}",
      "withoutUsername": "[{name}]({profileUrl})"
    }
  },
  "notifications": {
    "receiptStored": {
      "message": [
        "📝 {editorName} \\(@{editorUsername}\\) {action} чек {receiptDescription} на суму {receiptAmount}",
        "👤 Платник: {payerName} \\(@{payerUsername}\\)",
        "{part}\\",
        "📑 Борги: /debts, чеки: /receipts",
        "",
        "{receiptUrl}"
      ],
      "description": "\"{description}\"",
      "noDescription": "без опису",
      "actions": {
        "added": "створив\\(ла\\)",
        "updated": "відредагував\\(ла\\)"
      },
      "part": "💵 Твоя частина в чеку: *{partAmount}*\n"
    },
    "receiptDeleted": {
      "message": [
        "❌ 📝 {editorName} \\(@{editorUsername}\\) видалив\\(ла\\) чек {receiptDescription} на суму *{receiptAmount}*",
        "👤 Платник: {payerName} \\(@{payerUsername}\\)",
        "📑 Борги: /debts, чеки: /receipts"
      ],
      "description": "\"{description}\"",
      "noDescription": "без опису"
    },
    "paymentStored": {
      "message": [
        "➡️ {editorName} \\(@{editorUsername}\\) {action} платіж на суму *{amount}*",
        "👤 Відправник: {senderName} \\(@{senderUsername}\\)",
        "👤 Отримувач: {receiverName} \\(@{receiverUsername}\\)",
        "📑 Борги: /debts, платежі: /payments"
      ],
      "actions": {
        "added": "створив\\(ла\\)",
        "updated": "відредагував\\(ла\\)"
      }
    },
    "paymentDeleted": {
      "message": [
        "❌ ➡️ {editorName} \\(@{editorUsername}\\) видалив\\(ла\\) платіж на суму *{amount}*",
        "👤 Відправник: {senderName} \\(@{senderUsername}\\)",
        "👤 Отримувач: {receiverName} \\(@{receiverUsername}\\)",
        "📑 Борги: /debts, платежі: /payments"
      ]
    }
  },
  "banks": {
    "privatbank": {
      "long": "🟩 Приватбанк",
      "short": "приватбанк"
    },
    "monobank": {
      "long": "⬛️ Монобанк",
      "short": "монобанк"
    }
  }
}